README.md
setup.py
roi/__init__.py
roi/cohort_analysis.py
roi.egg-info/PKG-INFO
roi.egg-info/SOURCES.txt
roi.egg-info/dependency_links.txt
roi.egg-info/top_level.txt