Metadata-Version: 2.1
Name: roi
Version: 0.0.4
Summary: Marketing ROI package
Home-page: https://github.com/pypa/sampleproject
Author: Harjot Singh Parmar
Author-email: hsparmar@uwaterloo.ca
License: UNKNOWN
Platform: UNKNOWN
Classifier: Programming Language :: Python :: 3
Classifier: License :: OSI Approved :: MIT License
Classifier: Operating System :: OS Independent
Requires-Python: >=3.6
